README.md
setup.py
human_readable_time/human_readable_time.py
human_readable_time.egg-info/PKG-INFO
human_readable_time.egg-info/SOURCES.txt
human_readable_time.egg-info/dependency_links.txt
human_readable_time.egg-info/top_level.txt