Metadata-Version: 2.1
Name: human-readable-time
Version: 0.1.4
Summary: A utility package for human-readable time conversion.
Home-page: https://github.com/MuGhasemi/human_readable_time
Author: Muhammad Ghasemi
Author-email: mughasemi2008@email.com
License: UNKNOWN
Platform: UNKNOWN
Classifier: Development Status :: 3 - Alpha
Classifier: Intended Audience :: Developers
Classifier: License :: OSI Approved :: MIT License
Classifier: Programming Language :: Python :: 3
Classifier: Programming Language :: Python :: 3.6
Classifier: Programming Language :: Python :: 3.7
Classifier: Programming Language :: Python :: 3.8
